<annotation>
	<folder>Brown spot</folder>
	<filename>Brown_spot_18.jpg</filename>
	<path>D:\shivani\college\capstone\rice_leaf_diseases\Brown spot\Brown_spot_18.jpg</path>
	<source>
		<database>Unknown</database>
	</source>
	<size>
		<width>359</width>
		<height>168</height>
		<depth>3</depth>
	</size>
	<segmented>0</segmented>
	<object>
		<name>brown_spot</name>
		<pose>Unspecified</pose>
		<truncated>0</truncated>
		<difficult>0</difficult>
		<bndbox>
			<xmin>3</xmin>
			<ymin>28</ymin>
			<xmax>319</xmax>
			<ymax>149</ymax>
		</bndbox>
	</object>
</annotation>
